rwpk/__init__.py
rwpk/languages.py
rwpk/rwpk.py
rwpk/languages/sindhi.txt
rwpk/languages/urdu.txt
rwpk-0.0.2.dist-info/METADATA
rwpk-0.0.2.dist-info/WHEEL
rwpk-0.0.2.dist-info/top_level.txt
rwpk-0.0.2.dist-info/RECORD
